{
  "timestamp": "2025-03-06 03:46:58",
  "estaciones": [
    {
      "nombre": "Pluviómetro en MC en Los Patojos, Rbla Benipila",
      "municipio": "Cartagena",
      "codigo": "06A11P01",
      "mediciones": {
        "ultima_hora": 5.30000019,
        "ultimas_3h": 13.0,
        "ultimas_6h": 14.10000038,
        "ultimas_12h": 18.5,
        "ultimas_24h": 40.40000153
      },
      "coordenadas": {
        "x": 675339,
        "y": 4165640
      }
    },
    {
      "nombre": "Pluviómetro en MC en Cedacero, Rbla La Azohía",
      "municipio": "Cartagena",
      "codigo": "06A13P01",
      "mediciones": {
        "ultima_hora": null,
        "ultimas_3h": null,
        "ultimas_6h": null,
        "ultimas_12h": 9.04399967,
        "ultimas_24h": 36.97399902
      },
      "coordenadas": {
        "x": 663554,
        "y": 4162150
      }
    }
  ]
}